{"config":{"imagePath":"./sourceImages/Image.jpg","gdLevel":"Image To GD","newLevel":false,"generateImageSave":true,"saveLocation":"./saves/cat","res":[75,105],"threshold":0.06,"incorperateThreshold":3,"whiteThreshold":245,"maxCallback":250,"assetRes":100,"overlapQuality":0.45,"passThreshold":0.45,"lowObjectCount":false,"bakeArtifacts":true,"protectWhites":false,"whiteIsTransparency":false,"cleanUpNonMerged":true,"editorLayer":"0","imageWidth":"175"},"totalObjects":955,"totalOverlap":11847,"allAssets":["square.png","tri2.png","diamond.png","tri1.png","tri3.png","tri4.png"],"vectorizeTime":9773}